add.v
module half_adder (output W, X, input Y, Z); 
    and (X, Y, Z);
    xor (W, Y, Z);
endmodule

module full_adder (output W, X, input Y, Z, C); 
    assign W = Y^Z^C;
    assign X = (Y & Z) + (C & Y) + ( C & Z );
endmodule


module add (A, B, F);

    input [2:0] A, B; 
    output [3:0]F;
    wire x0,x1;
    half_adder H1(F[0],x0,A[0],B[0]);
    full_adder F1(F[1],x1,A[1],B[1], x0);
    full_adder F2(F[2],F[3],A[2],B[2], x1);

endmodule

add_tb.v
`timescale 1ns / 1ns
`include "add.v"

module add_tb;

    reg [2:0] A, B;
    wire [3:0]F;

    add uut(A, B, F);

    initial begin

        $dumpfile("add_tb.vcd");
        $dumpvars(0, add_tb);

        {A, B} = 6'b000000; #1;
        {A, B} = 6'b001000; #1;
        {A, B} = 6'b010000; #1;
        {A, B} = 6'b011000; #1;
        {A, B} = 6'b100000; #1;
        {A, B} = 6'b101000; #1;
        {A, B} = 6'b110000; #1;
        {A, B} = 6'b111000; #1;
        {A, B} = 6'b000001; #1;
        {A, B} = 6'b001001; #1;
        {A, B} = 6'b010001; #1;
        {A, B} = 6'b011001; #1;
        {A, B} = 6'b100001; #1;
        {A, B} = 6'b101001; #1;
        {A, B} = 6'b110001; #1;
        {A, B} = 6'b111001; #1;
        {A, B} = 6'b000010; #1;
        {A, B} = 6'b001010; #1;
        {A, B} = 6'b010010; #1;
        {A, B} = 6'b011010; #1;
        {A, B} = 6'b100010; #1;
        {A, B} = 6'b101010; #1;
        {A, B} = 6'b110010; #1;
        {A, B} = 6'b111010; #1;
        {A, B} = 6'b000011; #1;
        {A, B} = 6'b001011; #1;
        {A, B} = 6'b010011; #1;
        {A, B} = 6'b011011; #1;
        {A, B} = 6'b100011; #1;
        {A, B} = 6'b101011; #1;
        {A, B} = 6'b110011; #1;
        {A, B} = 6'b111011; #1;
        {A, B} = 6'b000100; #1;
        {A, B} = 6'b001100; #1;
        {A, B} = 6'b010100; #1;
        {A, B} = 6'b011100; #1;
        {A, B} = 6'b100100; #1;
        {A, B} = 6'b101100; #1;
        {A, B} = 6'b110100; #1;
        {A, B} = 6'b111100; #1;
        {A, B} = 6'b000101; #1;
        {A, B} = 6'b001101; #1;
        {A, B} = 6'b010101; #1;
        {A, B} = 6'b011101; #1;
        {A, B} = 6'b100101; #1;
        {A, B} = 6'b101101; #1;
        {A, B} = 6'b110101; #1;
        {A, B} = 6'b111101; #1;
        {A, B} = 6'b000110; #1;
        {A, B} = 6'b001110; #1;
        {A, B} = 6'b010110; #1;
        {A, B} = 6'b011110; #1;
        {A, B} = 6'b100110; #1;
        {A, B} = 6'b101110; #1;
        {A, B} = 6'b110110; #1;
        {A, B} = 6'b111110; #1;
        {A, B} = 6'b000111; #1;
        {A, B} = 6'b001111; #1;
        {A, B} = 6'b010111; #1;
        {A, B} = 6'b011111; #1;
        {A, B} = 6'b100111; #1;
        {A, B} = 6'b101111; #1;
        {A, B} = 6'b110111; #1;
        {A, B} = 6'b111111; #1;
 

        $display("Test Completed");
    end

endmodule

add_tb.vcd
$date
	Fri Nov 04 11:22:59 2022
$end
$version
	Icarus Verilog
$end
$timescale
	1ns
$end
$scope module add_tb $end
$var wire 4 ! F [3:0] $end
$var reg 3 " A [2:0] $end
$var reg 3 # B [2:0] $end
$scope module uut $end
$var wire 3 $ A [2:0] $end
$var wire 3 % B [2:0] $end
$var wire 4 & F [3:0] $end
$var wire 1 ' x0 $end
$var wire 1 ( x1 $end
$scope module H1 $end
$var wire 1 ) W $end
$var wire 1 ' X $end
$var wire 1 * Y $end
$var wire 1 + Z $end
$upscope $end
$scope module F1 $end
$var wire 1 ' C $end
$var wire 1 , W $end
$var wire 1 ( X $end
$var wire 1 - Y $end
$var wire 1 . Z $end
$upscope $end
$scope module F2 $end
$var wire 1 ( C $end
$var wire 1 / W $end
$var wire 1 0 X $end
$var wire 1 1 Y $end
$var wire 1 2 Z $end
$upscope $end
$upscope $end
$upscope $end
$enddefinitions $end
#0
$dumpvars
02
01
00
0/
0.
0-
0,
0+
0*
0)
0(
0'
b0 &
b0 %
b0 $
b0 #
b0 "
b0 !
$end
#1
1)
b1 !
b1 &
1*
b1 "
b1 $
#2
1,
0)
b10 !
b10 &
0*
1-
b10 "
b10 $
#3
1)
b11 !
b11 &
1*
b11 "
b11 $
#4
0,
1/
0)
b100 !
b100 &
0*
0-
11
b100 "
b100 $
#5
1)
b101 !
b101 &
1*
b101 "
b101 $
#6
1,
0)
b110 !
b110 &
0*
1-
b110 "
b110 $
#7
1)
b111 !
b111 &
1*
b111 "
b111 $
#8
0,
0/
b1 !
b1 &
0*
0-
01
1+
b0 "
b0 $
b1 #
b1 %
#9
1,
1'
0)
b10 !
b10 &
1*
b1 "
b1 $
#10
0/
0'
1)
b11 !
b11 &
0(
0*
1-
b10 "
b10 $
#11
1/
0,
1(
1'
0)
b100 !
b100 &
1*
b11 "
b11 $
#12
0'
1)
0(
00
b101 !
b101 &
0*
0-
11
b100 "
b100 $
#13
1,
1'
0)
b110 !
b110 &
1*
b101 "
b101 $
#14
1/
00
0'
1)
b111 !
b111 &
0(
0*
1-
b110 "
b110 $
#15
0/
10
0,
1(
1'
0)
b1000 !
b1000 &
1*
b111 "
b111 $
#16
1,
0/
00
b10 !
b10 &
0'
0(
0*
0-
01
0+
1.
b0 "
b0 $
b10 #
b10 %
#17
1)
b11 !
b11 &
1*
b1 "
b1 $
#18
0,
1/
0)
b100 !
b100 &
1(
0*
1-
b10 "
b10 $
#19
1)
b101 !
b101 &
1*
b11 "
b11 $
#20
1,
0)
0(
00
b110 !
b110 &
0*
0-
11
b100 "
b100 $
#21
1)
b111 !
b111 &
1*
b101 "
b101 $
#22
0,
0/
10
0)
b1000 !
b1000 &
1(
0*
1-
b110 "
b110 $
#23
1)
b1001 !
b1001 &
1*
b111 "
b111 $
#24
1,
0(
00
b11 !
b11 &
0*
0-
01
1+
b0 "
b0 $
b11 #
b11 %
#25
1/
0,
1(
1'
0)
b100 !
b100 &
1*
b1 "
b1 $
#26
0'
1)
b101 !
b101 &
1(
0*
1-
b10 "
b10 $
#27
1,
1(
1'
0)
b110 !
b110 &
1*
b11 "
b11 $
#28
1/
0'
1)
0(
00
b111 !
b111 &
0*
0-
11
b100 "
b100 $
#29
0/
10
0,
1(
1'
0)
b1000 !
b1000 &
1*
b101 "
b101 $
#30
0'
1)
b1001 !
b1001 &
1(
0*
1-
b110 "
b110 $
#31
1,
1(
1'
0)
b1010 !
b1010 &
1*
b111 "
b111 $
#32
0,
1/
0'
0(
00
b100 !
b100 &
0*
0-
01
0+
0.
12
b0 "
b0 $
b100 #
b100 %
#33
1)
b101 !
b101 &
1*
b1 "
b1 $
#34
1,
0)
b110 !
b110 &
0*
1-
b10 "
b10 $
#35
1)
b111 !
b111 &
1*
b11 "
b11 $
#36
0,
0/
0)
10
b1000 !
b1000 &
0*
0-
11
b100 "
b100 $
#37
1)
b1001 !
b1001 &
1*
b101 "
b101 $
#38
1,
0)
b1010 !
b1010 &
0*
1-
b110 "
b110 $
#39
1)
b1011 !
b1011 &
1*
b111 "
b111 $
#40
0,
1/
00
b101 !
b101 &
0*
0-
01
1+
b0 "
b0 $
b101 #
b101 %
#41
1,
1'
0)
b110 !
b110 &
1*
b1 "
b1 $
#42
1/
00
0'
1)
b111 !
b111 &
0(
0*
1-
b10 "
b10 $
#43
0/
10
0,
1(
1'
0)
b1000 !
b1000 &
1*
b11 "
b11 $
#44
0'
1)
0(
10
b1001 !
b1001 &
0*
0-
11
b100 "
b100 $
#45
1,
1'
0)
b1010 !
b1010 &
1*
b101 "
b101 $
#46
0/
10
0'
1)
b1011 !
b1011 &
0(
0*
1-
b110 "
b110 $
#47
1/
10
0,
1(
1'
0)
b1100 !
b1100 &
1*
b111 "
b111 $
#48
1,
1/
00
b110 !
b110 &
0'
0(
0*
0-
01
0+
1.
b0 "
b0 $
b110 #
b110 %
#49
1)
b111 !
b111 &
1*
b1 "
b1 $
#50
0,
0/
10
0)
b1000 !
b1000 &
1(
0*
1-
b10 "
b10 $
#51
1)
b1001 !
b1001 &
1*
b11 "
b11 $
#52
1,
0)
0(
10
b1010 !
b1010 &
0*
0-
11
b100 "
b100 $
#53
1)
b1011 !
b1011 &
1*
b101 "
b101 $
#54
0,
1/
10
0)
b1100 !
b1100 &
1(
0*
1-
b110 "
b110 $
#55
1)
b1101 !
b1101 &
1*
b111 "
b111 $
#56
1,
0(
00
b111 !
b111 &
0*
0-
01
1+
b0 "
b0 $
b111 #
b111 %
#57
0/
10
0,
1(
1'
0)
b1000 !
b1000 &
1*
b1 "
b1 $
#58
0'
1)
b1001 !
b1001 &
1(
0*
1-
b10 "
b10 $
#59
1,
1(
1'
0)
b1010 !
b1010 &
1*
b11 "
b11 $
#60
0/
0'
1)
0(
10
b1011 !
b1011 &
0*
0-
11
b100 "
b100 $
#61
1/
10
0,
1(
1'
0)
b1100 !
b1100 &
1*
b101 "
b101 $
#62
0'
1)
b1101 !
b1101 &
1(
0*
1-
b110 "
b110 $
#63
1,
1(
1'
0)
b1110 !
b1110 &
1*
b111 "
b111 $
